django_tango-0.10.0.dist-info/METADATA
django_tango-0.10.0.dist-info/RECORD
django_tango-0.10.0.dist-info/WHEEL
django_tango-0.10.0.dist-info/top_level.txt
tango_user/__init__.py
tango_user/admin.py
tango_user/filters.py
tango_user/forms.py
tango_user/models.py
tango_user/tests.py
tango_user/urls.py
tango_user/views.py
tango_user/management/__init__.py
tango_user/management/commands/__init__.py
tango_user/management/commands/send_digest.py
tango_user/templatetags/__init__.py
tango_user/templatetags/user_tags.py
video/__init__.py
video/admin.py
video/forms.py
video/helpers.py
video/managers.py
video/models.py
video/tests.py
video/urls.py
video/views.py
video/templates/video/base.html
video/templates/video/gallery_list.html
video/templates/video/video_detail.html
video/templates/video/video_detail_boxed.html
video/templates/video/video_list.html
video/templates/video/includes/second.html
video/templates/video/includes/show_video.html
video/templatetags/__init__.py
video/templatetags/video_tags.py
