Metadata-Version: 1.1
Name: django-tango
Version: 0.10.0
Summary: Faster, simpler Django content management.
Home-page: https://github.com/tBaxter/Tango
Author: Tim Baxter
Author-email: mail.baxter@gmail.com
License: MIT
Platform: UNKNOWN
Classifier: Development Status :: 4 - Beta
Classifier: Environment :: Web Environment
Classifier: Framework :: Django
Classifier: Intended Audience :: Developers
Classifier: License :: OSI Approved :: MIT License
Classifier: Programming Language :: Python
Classifier: Programming Language :: Python :: 2.7
Classifier: Programming Language :: Python :: 3.4
